tasx/__init__.py
tasx/base_client.py
tasx/enums.py
tasx/exceptions.py
tasx/interface_models.py
tasx/mixins/__init__.py
tasx/mixins/_shared.py
tasx/mixins/provider_sync.py
tasx/mixins/task_message_read.py
tasx/mixins/task_read.py
tasx/mixins/task_run_read.py
tasx/provider/__init__.py
tasx/provider/core.py
tasx/provider/utils.py
tasx/registry.py
tasx/runner.py
tasx/tasx_client.py
tasx/utils.py
tasx-0.0.4.dist-info/LICENSE
tasx-0.0.4.dist-info/METADATA
tasx-0.0.4.dist-info/WHEEL
tasx-0.0.4.dist-info/RECORD
